{"ts":1781960188851,"data":[{"n":"טוקיו","kj":"東","t":21.2,"c":63,"mx":22.6,"mn":20.1,"ss":"19:00"},{"n":"קיוטו","kj":"京","t":22.2,"c":2,"mx":24.3,"mn":22.2,"ss":"19:13"}],"forecast":{"tokyo":{"2026-06-23":{"c":3,"mx":24.4,"mn":18.4,"pp":12},"2026-06-24":{"c":51,"mx":25.6,"mn":16.5,"pp":51},"2026-06-25":{"c":55,"mx":25,"mn":20.1,"pp":78},"2026-06-26":{"c":95,"mx":25.9,"mn":20.5,"pp":73},"2026-06-27":{"c":51,"mx":29.1,"mn":20.9,"pp":37},"2026-06-28":{"c":51,"mx":28.2,"mn":21.2,"pp":45},"2026-06-29":{"c":3,"mx":27.5,"mn":20.9,"pp":30},"2026-06-30":{"c":51,"mx":25.8,"mn":21.2,"pp":29},"2026-07-01":{"c":80,"mx":28.1,"mn":21.3,"pp":43},"2026-07-02":{"c":53,"mx":29.3,"mn":22.4,"pp":40},"2026-07-03":{"c":95,"mx":29,"mn":22.9,"pp":48}},"kyoto":{"2026-06-23":{"c":3,"mx":27.2,"mn":19.1,"pp":4},"2026-06-24":{"c":3,"mx":26.9,"mn":16.7,"pp":41},"2026-06-25":{"c":95,"mx":22.7,"mn":20.2,"pp":71},"2026-06-26":{"c":95,"mx":26.6,"mn":20.7,"pp":81},"2026-06-27":{"c":3,"mx":29.2,"mn":20.2,"pp":47},"2026-06-28":{"c":3,"mx":29.9,"mn":18.8,"pp":43},"2026-06-29":{"c":53,"mx":27.3,"mn":19.5,"pp":35},"2026-06-30":{"c":95,"mx":27.9,"mn":21.3,"pp":53},"2026-07-01":{"c":95,"mx":27.2,"mn":22.1,"pp":68},"2026-07-02":{"c":95,"mx":27.7,"mn":22.6,"pp":74},"2026-07-03":{"c":95,"mx":26.9,"mn":22.6,"pp":80}},"nara":{"2026-06-23":{"c":3,"mx":26.8,"mn":19.2,"pp":6},"2026-06-24":{"c":3,"mx":27.3,"mn":17.6,"pp":45},"2026-06-25":{"c":95,"mx":23,"mn":20.5,"pp":75},"2026-06-26":{"c":96,"mx":26.8,"mn":21.1,"pp":84},"2026-06-27":{"c":51,"mx":28,"mn":20.6,"pp":49},"2026-06-28":{"c":3,"mx":28.6,"mn":20.4,"pp":48},"2026-06-29":{"c":51,"mx":26.8,"mn":19.7,"pp":35},"2026-06-30":{"c":95,"mx":25.2,"mn":21.7,"pp":47},"2026-07-01":{"c":96,"mx":26.7,"mn":22.4,"pp":59},"2026-07-02":{"c":80,"mx":28.5,"mn":23.1,"pp":69},"2026-07-03":{"c":80,"mx":26.8,"mn":22.5,"pp":76}}}}